superduperreload/__init__.py
superduperreload/_version.py
superduperreload/functional_reload.py
superduperreload/magics.py
superduperreload/patching.py
superduperreload/superduperreload.py
superduperreload/utils.py
superduperreload/version.py
superduperreload_core-0.0.6.dist-info/METADATA
superduperreload_core-0.0.6.dist-info/WHEEL
superduperreload_core-0.0.6.dist-info/top_level.txt
superduperreload_core-0.0.6.dist-info/RECORD
