Metadata-Version: 2.1
Name: superduperreload-core
Version: 0.0.6
Summary: Backend package for superduperreload's core functionality
Home-page: https://github.com/ipyflow/superduperreload
Author: Stephen Macke
Author-email: stephen.macke@gmail.com
License: BSD-3-Clause
Classifier: Development Status :: 3 - Alpha
Classifier: Intended Audience :: Developers
Classifier: License :: OSI Approved :: BSD License
Classifier: Natural Language :: English
Classifier: Programming Language :: Python :: 3.6
Classifier: Programming Language :: Python :: 3.7
Classifier: Programming Language :: Python :: 3.8
Classifier: Programming Language :: Python :: 3.9
Classifier: Programming Language :: Python :: 3.10
Classifier: Programming Language :: Python :: 3.11
Classifier: Programming Language :: Python :: 3.12
Requires-Python: >=3.6
Requires-Dist: ipython
Requires-Dist: pyccolo ==0.0.49
Requires-Dist: traitlets
Provides-Extra: dev
Requires-Dist: build ; extra == 'dev'
Requires-Dist: pycln ; extra == 'dev'
Requires-Dist: twine ; extra == 'dev'
Requires-Dist: versioneer ; extra == 'dev'
Requires-Dist: flake8 ; extra == 'dev'
Requires-Dist: flake8-no-implicit-concat ; extra == 'dev'
Requires-Dist: isort ; extra == 'dev'
Requires-Dist: mypy ; extra == 'dev'
Requires-Dist: numpy ; extra == 'dev'
Requires-Dist: pytest ; extra == 'dev'
Requires-Dist: pytest-cov ; extra == 'dev'
Requires-Dist: types-dataclasses ; extra == 'dev'
Provides-Extra: test
Requires-Dist: flake8 ; extra == 'test'
Requires-Dist: flake8-no-implicit-concat ; extra == 'test'
Requires-Dist: isort ; extra == 'test'
Requires-Dist: mypy ; extra == 'test'
Requires-Dist: numpy ; extra == 'test'
Requires-Dist: pytest ; extra == 'test'
Requires-Dist: pytest-cov ; extra == 'test'
Requires-Dist: types-dataclasses ; extra == 'test'
Provides-Extra: typecheck
Requires-Dist: mypy ; extra == 'typecheck'
